timecontrol/__init__.py
timecontrol/_version.py
timecontrol/command.py
timecontrol/eventlog.py
timecontrol/overlimiter.py
timecontrol/underlimiter.py
timecontrol-0.2.2.dist-info/LICENSE
timecontrol-0.2.2.dist-info/METADATA
timecontrol-0.2.2.dist-info/WHEEL
timecontrol-0.2.2.dist-info/top_level.txt
timecontrol-0.2.2.dist-info/RECORD
