Metadata-Version: 2.1
Name: timecontrol
Version: 0.2.2
Summary: Python library to control time in your async application
Home-page: https://github.com/asmodehn/timecontrol
Author: AlexV
Author-email: asmodehn@gmail.com
License: UNKNOWN
Platform: UNKNOWN
Requires-Dist: aiounittest
